<annotation>
	<folder>images</folder>
	<filename>mixaaaaaa2.jpg</filename>
	<path>C:\XvChenYe\data0\images\mixaaaaaa2.jpg</path>
	<source>
		<database>Unknown</database>
	</source>
	<size>
		<width>640</width>
		<height>480</height>
		<depth>3</depth>
	</size>
	<segmented>0</segmented>
	<object>
		<name>China</name>
		<pose>Unspecified</pose>
		<truncated>0</truncated>
		<difficult>0</difficult>
		<bndbox>
			<xmin>222</xmin>
			<ymin>107</ymin>
			<xmax>393</xmax>
			<ymax>225</ymax>
		</bndbox>
	</object>
	<object>
		<name>Mooli</name>
		<pose>Unspecified</pose>
		<truncated>0</truncated>
		<difficult>0</difficult>
		<bndbox>
			<xmin>172</xmin>
			<ymin>266</ymin>
			<xmax>274</xmax>
			<ymax>374</ymax>
		</bndbox>
	</object>
	<object>
		<name>Mooli</name>
		<pose>Unspecified</pose>
		<truncated>0</truncated>
		<difficult>0</difficult>
		<bndbox>
			<xmin>386</xmin>
			<ymin>264</ymin>
			<xmax>491</xmax>
			<ymax>383</ymax>
		</bndbox>
	</object>
</annotation>
