<annotation>
	<folder>imagess</folder>
	<filename>Bottle68_0.jpg</filename>
	<path>../data/annotations/Bottle68_0.jpg</path>
	<source>
		<database>Unknown</database>
	</source>
	<size>
		<width>640</width>
		<height>480</height>
		<depth>3</depth>
	</size>
	<segmented>0</segmented>
	<object>
		<name>Bottle</name>
		<pose>Unspecified</pose>
		<truncated>1</truncated>
		<difficult>0</difficult>
		<bndbox>
			<xmin>404</xmin>
			<ymin>57</ymin>
			<xmax>555</xmax>
			<ymax>154</ymax>
		</bndbox>
	</object>
</annotation>